mopup/__init__.py
mopup/__main__.py
mopup/py.typed
mopup-2024.8.9.1.dist-info/LICENSE.rst
mopup-2024.8.9.1.dist-info/METADATA
mopup-2024.8.9.1.dist-info/WHEEL
mopup-2024.8.9.1.dist-info/entry_points.txt
mopup-2024.8.9.1.dist-info/RECORD
