Metadata-Version: 2.1
Name: MOPUp
Version: 2024.8.9.1
Summary: MOPUp
Home-page: https://github.com/glyph/MOPUp
License: MIT
Author: Glyph Lefkowitz
Author-email: glyph@glyph.im
Requires-Python: >=3.8,<4.0
Classifier: Development Status :: 3 - Alpha
Classifier: License :: OSI Approved :: MIT License
Classifier: Programming Language :: Python :: 3
Classifier: Programming Language :: Python :: 3.8
Classifier: Programming Language :: Python :: 3.9
Classifier: Programming Language :: Python :: 3.10
Classifier: Programming Language :: Python :: 3.11
Classifier: Programming Language :: Python :: 3.12
Requires-Dist: certifi (>=2024.6.2,<2025.0.0)
Requires-Dist: click (>=8.0.1)
Requires-Dist: html5lib (>=1.1)
Requires-Dist: hyperlink
Requires-Dist: packaging (>=24.0,<25.0)
Requires-Dist: requests (>=2.27.1)
Requires-Dist: rich (>=12.4.4,<14.0.0)
Requires-Dist: types-click (>=7.1.8,<8.0.0)
Project-URL: Changelog, https://github.com/glyph/MOPUp/releases
Project-URL: Documentation, https://MOPUp.readthedocs.io
Project-URL: Repository, https://github.com/glyph/MOPUp
